mcp_test/__init__.py
mcp_test/server.py
mcp_echo_server-0.1.1.dist-info/METADATA
mcp_echo_server-0.1.1.dist-info/WHEEL
mcp_echo_server-0.1.1.dist-info/entry_points.txt
mcp_echo_server-0.1.1.dist-info/RECORD
