Metadata-Version: 2.4
Name: mcp-echo-server
Version: 0.1.1
Summary: A simple MCP server with an echo tool
Requires-Python: >=3.12
Requires-Dist: mcp>=1.0.0
